python_hindi/__init__.py
python_hindi/__main__.py
python_hindi/error_hook.py
python_hindi/hindi_data.py
python_hindi/hook.py
python_hindi/ipython.py
python_hindi-0.1.3.dist-info/entry_points.txt
python_hindi-0.1.3.dist-info/METADATA
python_hindi-0.1.3.dist-info/WHEEL
python_hindi-0.1.3.dist-info/RECORD
